tassistant_bot/__init__.py
tassistant_bot/__main__.py
tassistant_bot/helpers/__init__.py
tassistant_bot/helpers/config.py
tassistant_bot/helpers/i18n/__init__.py
tassistant_bot/helpers/i18n/base.py
tassistant_bot/loader.py
tassistant_bot/modules/.gitkeep
tassistant_bot/scenarios/__init__.py
tassistant_bot/scenarios/base.py
tassistant_bot-0.2.5.dist-info/METADATA
tassistant_bot-0.2.5.dist-info/WHEEL
tassistant_bot-0.2.5.dist-info/entry_points.txt
tassistant_bot-0.2.5.dist-info/RECORD
