Metadata-Version: 2.1
Name: tassistant-bot
Version: 0.2.5
Summary: 
Author: kinsoRick
Author-email: kmasnaveev@gmail.com
Requires-Python: >=3.10,<4.0
Classifier: Programming Language :: Python :: 3
Classifier: Programming Language :: Python :: 3.10
Classifier: Programming Language :: Python :: 3.11
Classifier: Programming Language :: Python :: 3.12
Requires-Dist: PyroTGFork (>=2.1.33.2,<3.0.0.0)
Requires-Dist: click (>=8.1.7,<9.0.0)
Requires-Dist: colorlog (>=6.8.2,<7.0.0)
Requires-Dist: gitpython (>=3.1.43,<4.0.0)
Requires-Dist: python-dotenv (>=1.0.1,<2.0.0)
Requires-Dist: tgcrypto (>=1.2.5,<2.0.0)
